{"stats":{"minecraft:mined":{"minecraft:grass_block":1},"minecraft:killed_by":{"minecraft:player":2},"minecraft:custom":{"minecraft:jump":25,"minecraft:time_since_rest":11619,"minecraft:leave_game":1,"minecraft:crouch_one_cm":1693,"minecraft:sprint_one_cm":2982,"minecraft:deaths":2,"minecraft:play_time":17969,"minecraft:damage_taken":530,"minecraft:time_since_death":11591,"minecraft:walk_one_cm":4322,"minecraft:sneak_time":147,"minecraft:total_world_time":17969,"minecraft:fly_one_cm":13288},"minecraft:picked_up":{"minecraft:dirt":1}},"DataVersion":4189}